routemaster/__init__.py
routemaster/__main__.py
routemaster/app.py
routemaster/cli.py
routemaster/conftest.py
routemaster/context.py
routemaster/cron.py
routemaster/cron_processors.py
routemaster/feeds.py
routemaster/gunicorn_application.py
routemaster/middleware.py
routemaster/text_utils.py
routemaster/time_utils.py
routemaster/timezones.py
routemaster/utils.py
routemaster/validation.py
routemaster/webhooks.py
routemaster/config/__init__.py
routemaster/config/exceptions.py
routemaster/config/loader.py
routemaster/config/model.py
routemaster/config/schema.yaml
routemaster/db/__init__.py
routemaster/db/initialisation.py
routemaster/db/model.py
routemaster/exit_conditions/__init__.py
routemaster/exit_conditions/__main__.py
routemaster/exit_conditions/analysis.py
routemaster/exit_conditions/error_display.py
routemaster/exit_conditions/evaluator.py
routemaster/exit_conditions/exceptions.py
routemaster/exit_conditions/operations.py
routemaster/exit_conditions/parser.py
routemaster/exit_conditions/peephole.py
routemaster/exit_conditions/prepositions.py
routemaster/exit_conditions/program.py
routemaster/exit_conditions/tokenizer.py
routemaster/logging/__init__.py
routemaster/logging/base.py
routemaster/logging/plugins.py
routemaster/logging/python_logger.py
routemaster/logging/split_logger.py
routemaster/server/__init__.py
routemaster/server/endpoints.py
routemaster/state_machine/__init__.py
routemaster/state_machine/actions.py
routemaster/state_machine/api.py
routemaster/state_machine/exceptions.py
routemaster/state_machine/gates.py
routemaster/state_machine/transitions.py
routemaster/state_machine/types.py
routemaster/state_machine/utils.py
routemaster-1.5.0.dist-info/LICENSE
routemaster-1.5.0.dist-info/METADATA
routemaster-1.5.0.dist-info/WHEEL
routemaster-1.5.0.dist-info/entry_points.txt
routemaster-1.5.0.dist-info/top_level.txt
routemaster-1.5.0.dist-info/RECORD
