Metadata-Version: 2.1
Name: routemaster
Version: 1.5.0
Summary: State machines as a service.
Home-page: https://github.com/thread/routemaster
Author: Thread
Author-email: tech@thread.com
License: MIT
Platform: UNKNOWN
Classifier: Development Status :: 2 - Pre-Alpha
Classifier: Environment :: Console
Classifier: Natural Language :: English
Classifier: Operating System :: POSIX
Classifier: Programming Language :: Python
Classifier: Programming Language :: Python :: 3 :: Only
Classifier: Programming Language :: Python :: 3.6
Classifier: Programming Language :: Python :: 3.7
Classifier: Programming Language :: Python :: 3.8
Classifier: Programming Language :: Python :: 3.9
Classifier: Topic :: Office/Business
License-File: LICENSE
Requires-Dist: click
Requires-Dist: layer-loader
Requires-Dist: pyyaml (>=5)
Requires-Dist: jsonschema (<3,>=2.6)
Requires-Dist: flask
Requires-Dist: psycopg2-binary
Requires-Dist: sqlalchemy
Requires-Dist: python-dateutil
Requires-Dist: alembic (>=0.9.6)
Requires-Dist: gunicorn (>=19.7)
Requires-Dist: schedule
Requires-Dist: freezegun
Requires-Dist: requests
Requires-Dist: networkx
Requires-Dist: dataclasses
Requires-Dist: typing-extensions (>=3.7.4)
